<cf:model  cf:cpu="cortex_a72" cf:name="root" cf:partition="0" cf:prefix="_p0_" xd:type="design" xmlns:cf="http_//www_xilinx_com/connections" xmlns:xd="http_//www_xilinx_com/xd" >
  <cf:block  cf:name="aieip" >
    <cf:port  cf:direction="in" cf:name="hdiff_in7" cf:portType="stream" >    </cf:port>
    <cf:port  cf:direction="out" cf:name="hdiff_out0" cf:portType="stream" >    </cf:port>
    <cf:port  cf:direction="in" cf:name="hdiff_in0" cf:portType="stream" >    </cf:port>
    <cf:port  cf:direction="in" cf:name="hdiff_in1" cf:portType="stream" >    </cf:port>
    <cf:port  cf:direction="in" cf:name="hdiff_in2" cf:portType="stream" >    </cf:port>
    <cf:port  cf:direction="in" cf:name="hdiff_in3" cf:portType="stream" >    </cf:port>
    <cf:port  cf:direction="in" cf:name="hdiff_in4" cf:portType="stream" >    </cf:port>
    <cf:port  cf:direction="in" cf:name="hdiff_in5" cf:portType="stream" >    </cf:port>
    <cf:port  cf:direction="in" cf:name="hdiff_in6" cf:portType="stream" >    </cf:port>  
  </cf:block>
  <cf:comp  cf:name="ai_engine_0" xd:componentRef="ai_engine" >  
  </cf:comp>
  <cf:instance  cf:blockName="aieip" cf:compName="ai_engine_0" cf:name="ai_engine_0" >
    <cf:portMap cf:blockPort="hdiff_in7" cf:compPort="S07_AXIS" cf:paddedWidth="32" xd:isRegistered="true" >    </cf:portMap>
    <cf:portMap cf:blockPort="hdiff_out0" cf:compPort="M00_AXIS" cf:paddedWidth="32" xd:isRegistered="true" >    </cf:portMap>
    <cf:portMap cf:blockPort="hdiff_in0" cf:compPort="S00_AXIS" cf:paddedWidth="32" xd:isRegistered="true" >    </cf:portMap>
    <cf:portMap cf:blockPort="hdiff_in1" cf:compPort="S01_AXIS" cf:paddedWidth="32" xd:isRegistered="true" >    </cf:portMap>
    <cf:portMap cf:blockPort="hdiff_in2" cf:compPort="S02_AXIS" cf:paddedWidth="32" xd:isRegistered="true" >    </cf:portMap>
    <cf:portMap cf:blockPort="hdiff_in3" cf:compPort="S03_AXIS" cf:paddedWidth="32" xd:isRegistered="true" >    </cf:portMap>
    <cf:portMap cf:blockPort="hdiff_in4" cf:compPort="S04_AXIS" cf:paddedWidth="32" xd:isRegistered="true" >    </cf:portMap>
    <cf:portMap cf:blockPort="hdiff_in5" cf:compPort="S05_AXIS" cf:paddedWidth="32" xd:isRegistered="true" >    </cf:portMap>
    <cf:portMap cf:blockPort="hdiff_in6" cf:compPort="S06_AXIS" cf:paddedWidth="32" xd:isRegistered="true" >    </cf:portMap>  
  </cf:instance>
</cf:model>